LICENSE.txt
MANIFEST.in
README.rst
setup.cfg
setup.py
Examples/jupyter_notebooks/00_Enhancing_the_ZOS_API_Interface.ipynb
Examples/jupyter_notebooks/01_Test_PyZOS_sync_ui_functionality.ipynb
Examples/jupyter_notebooks/02_KB_article_How_to_create_a_User_Analysis_using_ZOS_API.ipynb
PyZOS.egg-info/PKG-INFO
PyZOS.egg-info/SOURCES.txt
PyZOS.egg-info/dependency_links.txt
PyZOS.egg-info/top_level.txt
pyzos/__init__.py
pyzos/ddeclient.py
pyzos/zos.py
pyzos/zosutils.py
pyzos/zos_obj_override/__init__.py
pyzos/zos_obj_override/i_analyses_methods.py
pyzos/zos_obj_override/ia__methods.py
pyzos/zos_obj_override/iar__methods.py
pyzos/zos_obj_override/ifields_methods.py
pyzos/zos_obj_override/ilderow_methods.py
pyzos/zos_obj_override/ilensdataeditor_methods.py
pyzos/zos_obj_override/ilocaloptimization_methods.py
pyzos/zos_obj_override/imeritfunctioneditor_methods.py
pyzos/zos_obj_override/iopticalsystemtools_methods.py
pyzos/zos_obj_override/isystemdata_methods.py
pyzos/zos_obj_override/izosapi_application_methods.py