Metadata-Version: 1.1
Name: PyZOS
Version: 0.0.60
Summary: Python interface for Zemax OpticStudio COM API (ZOS-API)
Home-page: https://github.com/pyzos/pyzos
Author: Indranil Sinharoy
Author-email: indranil_leo@yahoo.com
License: MIT
Keywords: zemax opticstudio extensions COM optics ZOS-API
Platform: UNKNOWN
Classifier: Intended Audience :: Science/Research
Classifier: Topic :: Scientific/Engineering
Classifier: Natural Language :: English
Classifier: Environment :: Win32 (MS Windows)
Classifier: License :: OSI Approved :: MIT License
Classifier: Operating System :: Microsoft :: Windows :: Windows 7
Classifier: Programming Language :: Python
Classifier: Programming Language :: Python :: 2.7
Classifier: Programming Language :: Python :: 3
Classifier: Programming Language :: Python :: 3.2
Classifier: Programming Language :: Python :: 3.3
Classifier: Programming Language :: Python :: 3.4
Classifier: Programming Language :: Python :: 3.5
Classifier: Topic :: Scientific/Engineering
